[
   {
      "id": 101,
      "name": "Casual Shoes",
      "price": 59.99,
      "description": "Comfortable and stylish casual shoes.",
      "color": "brown",
      "size": "10",
      "material": "leather",
      "image": "https://i.ibb.co/27t7ddr/240-F-209822653-Fzoff04b-Z8-QHnse-FCHy7vk-Lm-Wl1m-IDHO.jpg",
      "brand": "Nike",
      "rating": 4.2,
      "subcategory": "shoes",
      "category": "man",
      "Quantity": 50
   },
   {
      "id": 108,
      "name": "Slim Fit Jeans",
      "price": 89.99,
      "description": "Stylish slim fit jeans.",
      "color": "blue",
      "material": "denim",
      "image": "https://i.ibb.co/ns9LtTZ/240-F-309556383-wf-Aujx-KOTj-Ur-J8e6p-Xfb-VEo-Ie-Vv1-Mkm8.jpg",
      "brand": "Levi's",
      "rating": 4.4,
      "subcategory": "jeans",
      "category": "man",
      "Quantity": 20
   },
   {
      "id": 105,
      "name": "Tote Handbag",
      "price": 89.99,
      "description": "Spacious and stylish tote handbag.",
      "color": "black",
      "material": "leather",
      "image": "https://i.ibb.co/FBKkLL4/240-F-202389840-Rt-Pc-E03-Pu-Fbdi-Af-AVi-DPTYWKr-Jw-Psa-N9.jpg",
      "brand": "Michael Kors",
      "rating": 3.8,
      "subcategory": "handbags",
      "category": "women",
      "Quantity": 60
   },
   {
      "id": 106,
      "name": "Cat-Eye Sunglasses",
      "price": 69.99,
      "description": "Trendy cat-eye sunglasses.",
      "color": "purple",
      "material": "plastic",
      "image": "https://i.ibb.co/23pvkZm/240-F-604987216-sh8-YSpm-Gqa-Ek4-Ux2-Byd-HOa-Mmfb-UC2-FZ9.jpg",
      "brand": "Gucci",
      "rating": 3.2,
      "subcategory": "sunglasses",
      "category": "women",
      "Quantity": 50
   },
   {
      "id": 103,
      "name": "Leather Watch",
      "price": 129.99,
      "description": "Elegant leather watch.",
      "color": "brown",
      "material": "leather",
      "image": "https://i.ibb.co/H7CzgNM/240-F-175510727-Yixe-Nz5a-E5-Aw-VZfcm-S6n-Sm2-MPXOk-Hk-Ug.jpg",
      "brand": "Fossil",
      "rating": 4.7,
      "subcategory": "watches",
      "category": "man",
      "Quantity": 50
   },
   {
      "id": 104,
      "name": "Aviator Sunglasses",
      "price": 59.99,
      "description": "Classic aviator sunglasses.",
      "color": "silver",
      "material": "metal",
      "image": "https://i.ibb.co/rZHRJD8/240-F-29366394-f5g-SZSPLs-VOehan6aj3-Aekqrmf-Qb-CFDh.jpg",
      "brand": "Ray-Ban",
      "rating": 4.3,
      "subcategory": "sunglasses",
      "category": "man",
      "Quantity": 10
   },
   {
      "id": 107,
      "name": "Cotton T-Shirt",
      "price": 24.99,
      "description": "Soft and comfortable cotton t-shirt.",
      "color": "white",
      "material": "cotton",
      "image": "https://i.ibb.co/Cb9v2Y0/240-F-597353168-u4tf-BDM5h-Xum-Wh-Jtsi-EA3-GE62o-Dv1j-HN.jpg",
      "brand": "Polo Ralph Lauren",
      "rating": 4.4,
      "subcategory": "tshirts",
      "category": "man",
      "Quantity": 50
   },
   {
      "id": 102,
      "name": "Sports Shoes",
      "price": 79.99,
      "description": "High-performance sports shoes.",
      "color": "black",
      "size": "11",
      "material": "synthetic",
      "image": "https://i.ibb.co/0KYfdnR/240-F-121166552-8-Oh-Rt-CSmjb-Ez-X6q-Mk-K8j-Vec-SGcv-Qe0-Sc.jpg",
      "brand": "Adidas",
      "rating": 4.9,
      "subcategory": "shoes",
      "category": "man",
      "Quantity": 50
   },
   {
      "id": 109,
      "name": "Elegant Dress",
      "price": 149.99,
      "description": "Elegant dress for special occasions.",
      "color": "red",
      "material": "silk",
      "image": "https://i.ibb.co/5vFckLZ/240-F-490470420-5-Cld-UGj-UELNHOJ2bk-VOssk-Ti-AYZm-EV0q.jpg",
      "brand": "Dolce & Gabbana",
      "rating": 4.9,
      "subcategory": "dresses",
      "category": "women",
      "Quantity": 50
   },
   {
      "id": 110,
      "name": "Kids' Baseball Cap",
      "price": 19.99,
      "description": "Stylish baseball cap for kids.",
      "color": "blue",
      "size": "S",
      "material": "cotton",
      "image": "https://i.ibb.co/zfYZPnt/240-F-186121194-cx-Uz1jwom-M2iaqv-MR6u-Mp-E7-DU52-Ip-BAH.jpg",
      "brand": "Gap",
      "rating": 4.2,
      "subcategory": "caps",
      "category": "kids",
      "Quantity": 50
   },
   {
      "id": 111,
      "name": "Kids' Fabric Belt",
      "price": 14.99,
      "description": "Colorful fabric belt for kids.",
      "color": "multi-color",
      "size": "One Size",
      "material": "fabric",
      "image": "https://i.ibb.co/805265M/240-F-501273578-lw7c-El98y3-Pbh-Pc2tz-AIGRRf-Zpq-U1hk-P.jpg",
      "brand": "H&M",
      "rating": 4.0,
      "subcategory": "belts",
      "category": "kids",
      "Quantity": 40
   },
   {
      "id": 112,
      "name": "Kids' Cotton T-Shirt",
      "price": 12.99,
      "description": "Comfortable cotton t-shirt for kids.",
      "color": "yellow",
      "material": "cotton",
      "image": "https://i.ibb.co/7pGDZ0w/240-F-245786759-DZq-Qt-Hz-RRJAAuiy6p-Q38noj-Ggrb-Qu-HKx.jpg",
      "brand": "Gap Kids",
      "rating": 4.3,
      "subcategory": "tshirts",
      "category": "kids",
      "Quantity": 50
   },
   {
      "id": 113,
      "name": "Kids' Denim Jeans",
      "price": 34.99,
      "description": "Stylish denim jeans for kids.",
      "color": "blue",
      "material": "denim",
      "image": "https://i.ibb.co/JrMCHKW/240-F-614233118-m-KQZl0-Bxl-XSPpfy-V7rgf7-Irojd-Xjk-Hgf.jpg",
      "brand": "Levi's Kids",
      "rating": 4.5,
      "subcategory": "jeans",
      "category": "kids",
      "Quantity": 50
   },
   {
      "id": 114,
      "name": "Running Shoes",
      "price": 89.99,
      "description": "Lightweight and comfortable running shoes.",
      "color": "gray",
      "size": "9.5",
      "material": "mesh",
      "image": "https://i.ibb.co/mSSns75/240-F-594437828-kj8-Kd-RMsl-U40u-ZY6h-XOW0-ZWfxff1ndn-B.jpg",
      "brand": "New Balance",
      "rating": 4.7,
      "subcategory": "shoes",
      "category": "man",
      "Quantity": 50
   },
   {
      "id": 115,
      "name": "Digital Sports Watch",
      "price": 49.99,
      "description": "Digital sports watch with multiple features.",
      "color": "black",
      "material": "plastic",
      "image": "https://i.ibb.co/DYFjb8t/240-F-410688200-K9-KBMh4cx-KCurv-Bo-Yn-O2q-CLYo-ZRVUj-De.jpg",
      "brand": "Casio",
      "rating": 4.5,
      "subcategory": "watches",
      "category": "man",
      "Quantity": 50
   },
   {
      "id": 116,
      "name": "Square Sunglasses",
      "price": 39.99,
      "description": "Trendy square sunglasses for men.",
      "color": "tortoise",
      "material": "plastic",
      "image": "https://i.ibb.co/YdbCBYS/240-F-224951162-K8-Nv05-Esedg-Udzw-Uprujo-FX8sy-Cojs-Cu.jpg",
      "brand": "Oakley",
      "rating": 4.4,
      "subcategory": "sunglasses",
      "category": "man",
      "Quantity": 50
   },
   {
      "id": 117,
      "name": "Crossbody Bag",
      "price": 109.99,
      "description": "Stylish and versatile crossbody bag for women.",
      "color": "beige",
      "material": "leather",
      "image": " https://i.ibb.co/DfPP6KZ/240-F-110045173-Qgm-A3gg5-Ow-Tl-LNQBqm-Pd-Fnkh6s-Pvsvt8.jpg",
      "brand": "Coach",
      "rating": 4.8,
      "subcategory": "handbags",
      "category": "women",
      "Quantity": 50
   },
   {
      "id": 118,
      "name": "Round Sunglasses",
      "price": 79.99,
      "description": "Chic round sunglasses for women.",
      "color": "rose gold",
      "material": "metal",
      "image": "https://i.ibb.co/PGgQ55g/240-F-604987088-MVd-Do-DMXADa5d-Ae-Ta-Bqfq7n-Nb9-Ultqfx.jpg",
      "brand": "Prada",
      "rating": 4.6,
      "subcategory": "sunglasses",
      "category": "women",
      "Quantity": 50
   },
   {
      "id": 119,
      "name": "Graphic Print T-Shirt",
      "price": 29.99,
      "description": "Cool graphic print t-shirt for men and women.",
      "color": "black",
      "material": "cotton",
      "image": "https://i.ibb.co/j3MDVkj/240-F-101778868-Hq-C4f-LRQ4-BY1-GDPz8-DSIPXecei7y-Iq-FP.jpg",
      "brand": "Supreme",
      "rating": 4.9,
      "subcategory": "tshirts",
      "category": "women",
      "Quantity": 50
   },
   {
      "id": 120,
      "name": "Slim Fit Jeans",
      "price": 94.99,
      "description": "Premium slim fit jeans for men and women.",
      "color": "black",
      "material": "denim",
      "image": "https://i.ibb.co/cDbfHjC/240-F-311229788-VRW3o-Efj-EP75zt9m26xq-G3w6-WRz-DQJGl.jpg",
      "brand": "Diesel",
      "rating": 4.7,
      "subcategory": "jeans",
      "category": "man",
      "Quantity": 50
   },
   {
      "id": 121,
      "name": "Cocktail Dress",
      "price": 249.99,
      "description": "Elegant cocktail dress for women.",
      "color": "navy blue",
      "material": "satin",
      "image": "https://i.ibb.co/hF6vM3s/240-F-368881299-zu-SAOta-Jgtj3-XLAS0a-HNm6tk-Nh8-WSoh-H.jpg",
      "brand": "Versace",
      "rating": 4.9,
      "subcategory": "dresses",
      "category": "women",
      "Quantity": 50
   },
   {
      "id": 122,
      "name": "Kids' Sneakers",
      "price": 49.99,
      "description": "Stylish and comfortable sneakers for kids.",
      "color": "pink",
      "size": "8",
      "material": "canvas",
      "image": "https://i.ibb.co/56pLSBF/240-F-502208226-wn8-UCWk-BLah-Axj-LZp-VKXqf1ru-Wwch-Y8i.jpg",
      "brand": "Vans",
      "rating": 4.5,
      "subcategory": "shoes",
      "category": "kids",
      "Quantity": 50
   },
   {
      "id": 123,
      "name": "Kids' Digital Watch",
      "price": 29.99,
      "description": "Digital watch with fun designs for kids.",
      "color": "blue",
      "material": "plastic",
      "image": "https://i.ibb.co/yXqbRmp/240-F-301933444-w-Yhk-Qtk8z-KFm-BITr8-Xv6n-YJn-U4ao51as.jpg",
      "brand": "Timex",
      "rating": 4.2,
      "subcategory": "watches",
      "category": "kids",
      "Quantity": 50
   },
   {
      "id": 124,
      "name": "Kids' Polka Dot Dress",
      "price": 39.99,
      "description": "Adorable polka dot dress for girls.",
      "color": "pink",
      "material": "cotton",
      "image": "https://i.ibb.co/VSmDszG/images.jpg",
      "brand": "GAP Kids",
      "rating": 4.6,
      "subcategory": "dresses",
      "category": "kids",
      "Quantity": 50
   },
   {
      "id": 125,
      "name": "Kids' Denim Shorts",
      "price": 24.99,
      "description": "Cute denim shorts for boys.",
      "color": "blue",
      "material": "denim",
      "image": "https://i.ibb.co/QX2Gszg/240-F-622032703-Cu-US5t7-DY8-Qt-VInx-J9w7-TZ3k-Vjv90-F9n.jpg",
      "brand": "OshKosh B'gosh",
      "rating": 4.3,
      "subcategory": "shorts",
      "category": "kids",
      "Quantity": 50
   },
   {
      "id": 501,
      "name": "Polo Shirt",
      "price": 34.99,
      "description": "Classic polo shirt for men.",
      "color": "blue",
      "material": "cotton",
      "image": "https://i.ibb.co/ZGKVh9x/240-F-490754831-vp-Bty3-FR8-AJnnkcp-Hkqs-Pb-YZTAdc-Hw0e-1.jpg",
      "brand": "Ralph Lauren",
      "rating": 4.8,
      "subcategory": "shirts",
      "category": "man",
      "Quantity": 50
   },
   {
      "id": 502,
      "name": "Denim Jacket",
      "price": 79.99,
      "description": "Stylish denim jacket for men.",
      "color": "blue",
      "material": "denim",
      "image": "https://i.ibb.co/bLJHqqy/240-F-468420798-ylop-WSXKz3x-Nv-VH7-AYFz-Lbvzbq-Y7e-PMe.jpg",
      "brand": "Levi's",
      "rating": 4.7,
      "subcategory": "jackets",
      "category": "man",
      "Quantity": 50
   },
   {
      "id": 503,
      "name": "Dress Shirt",
      "price": 49.99,
      "description": "Formal shirt",
      "color": "white",
      "material": "cotton",
      "image": "https://i.ibb.co/MM9Gp7s/240-F-250849890-qx-H2-Mudf-Mq5-AFSq-Hr-Op5o-A9-Nqyk-T14-Ti.jpg",
      "brand": "Calvin Klein",
      "rating": 4.6,
      "subcategory": "shirts",
      "category": "man",
      "Quantity": 50
   },
   {
      "id": 504,
      "name": "Floral Maxi Dress",
      "price": 89.99,
      "description": "floral maxi dress.",
      "color": "purple",
      "material": "polyester",
      "image": "https://i.ibb.co/SRGcPcx/240-F-484876187-u6-HIl-Cg-A2i-Zdfko-Oamu-Qa43-OJH2za-DVR.jpg",
      "brand": "Free People",
      "rating": 4.9,
      "subcategory": "dresses",
      "category": "women",
      "Quantity": 50
   },
   {
      "id": 505,
      "name": "Leather Crossbody Bag",
      "price": 109.99,
      "description": "Stylish leather crossbody bag.",
      "color": "black",
      "material": "leather",
      "image": "  https://i.ibb.co/k9QM4fG/240-F-612957428-DY5ng-Lri-UJql3-C0-Xi8-Uo-X1n4-Cjc-Yi-Fgh.jpg",
      "brand": "Michael Kors",
      "rating": 4.8,
      "subcategory": "handbags",
      "category": "women",
      "Quantity": 50
   },
   {
      "id": 506,
      "name": "Ripped Skinny Jeans",
      "price": 69.99,
      "description": "Trendy ripped skinny jeans.",
      "color": "blue",
      "material": "denim",
      "image": "https://i.ibb.co/RTk1wBK/240-F-303613999-boelu-Bi6e7-QIa47sg2-CAx-UNT5-VUw-Wu-Fy.jpg",
      "brand": "Guess",
      "rating": 4.6,
      "subcategory": "jeans",
      "category": "women",
      "Quantity": 50
   },
   {
      "id": 507,
      "name": "Striped T-Shirt",
      "price": 24.99,
      "description": "Casual striped t-shirt.",
      "color": "red",
      "material": "cotton",
      "image": "https://i.ibb.co/CWdC7Q8/240-F-368875128-jv-C7b3ds-Ul1-PPG3k-FMk-T8x-Of3p-Jr-QLaz.jpg",
      "brand": "H&M",
      "rating": 4.5,
      "subcategory": "tshirts",
      "category": "women",
      "Quantity": 50
   },
   {
      "id": 508,
      "name": "Printed Hoodie",
      "price": 49.99,
      "description": "Cozy printed hoodie.",
      "color": "gray",
      "material": "fleece",
      "image": "https://i.ibb.co/D83sfCc/240-F-613479910-dmpm-OHEed-E0nens-Ku-UQq-Zyb0w-Ec-Gm-Gi1.jpg",
      "brand": "Nike",
      "rating": 4.7,
      "subcategory": "hoodies",
      "category": "man",
      "Quantity": 50
   },
   {
      "id": 509,
      "name": "Kids' Striped Dress",
      "price": 29.99,
      "description": "Adorable striped dress for kids.",
      "color": "pink",
      "material": "cotton",
      "image": "https://i.ibb.co/PYC7qGC/images-4.jpg",
      "brand": "Carter's",
      "rating": 4.5,
      "subcategory": "dresses",
      "category": "kids",
      "Quantity": 50
   },
   {
      "id": 510,
      "name": "Kids' Printed T-Shirt",
      "price": 14.99,
      "description": "Fun printed t-shirt for kids.",
      "color": "yellow",
      "material": "cotton",
      "image": "https://i.ibb.co/hDxhH1n/images-1.jpg",
      "brand": "GAP Kids",
      "rating": 4.4,
      "subcategory": "tshirts",
      "category": "kids",
      "Quantity": 50
   },
   {
      "id": 727,
      "name": "Tie-Dye T-Shirt",
      "price": 29.99,
      "description": "Trendy tie-dye t-shirt.",
      "color": "rainbow",
      "material": "cotton",
      "image": "https://i.ibb.co/930RPpx/240-F-186678530-2-Ul-YEtp-BKs-EU1-Jbso5f5z-KBk-Vbu-R1gvt.jpg",
      "brand": "Urban Outfitters",
      "rating": 4.6,
      "subcategory": "tshirts",
      "category": "man",
      "Quantity": 50
   },
   {
      "id": 728,
      "name": "Boat Shoes",
      "price": 59.99,
      "description": "Classic boat shoes.",
      "color": "brown",
      "material": "leather",
      "image": "https://i.ibb.co/27t7ddr/240-F-209822653-Fzoff04b-Z8-QHnse-FCHy7vk-Lm-Wl1m-IDHO.jpg",
      "brand": "Sperry",
      "rating": 4.8,
      "subcategory": "shoes",
      "category": "man",
      "Quantity": 50
   },
   {
      "id": 729,
      "name": "Kimono",
      "price": 39.99,
      "description": "Elegant kimono.",
      "color": "floral",
      "material": "polyester",
      "image": "https://i.ibb.co/H7mXKyQ/240-F-213782882-T6-V0-EGER5u-UBHK53cz-Km-Guk-S4-Oz-Uz-B9-I.jpg",
      "brand": "Nasty Gal",
      "rating": 4.7,
      "subcategory": "jackets",
      "category": "women",
      "Quantity": 50
   },
   {
      "id": 731,
      "name": "Striped Shirt",
      "price": 29.99,
      "description": "Classic striped shirt.",
      "color": "blue/white",
      "material": "cotton",
      "image": "https://i.ibb.co/Qr33q0M/240-F-126917876-QVFao2-TKEq-Qej-DDvx-Sdd-OVUXw-U0vsnd9.jpg",
      "brand": "Gap",
      "rating": 4.7,
      "subcategory": "shirts",
      "category": "man",
      "Quantity": 50
   },
   {
      "id": 732,
      "name": "Sweater Dress",
      "price": 49.99,
      "description": "Cozy sweater dress.",
      "color": "gray",
      "material": "acrylic",
      "image": "https://i.ibb.co/x7bqmmH/240-F-127154936-1z-PSMtn-W4-Vtr4-Whoe7x-NCWw-Z6-Ay7mk-Bd.jpg",
      "brand": "H&M",
      "rating": 4.6,
      "subcategory": "dresses",
      "category": "women",
      "Quantity": 50
   },
   {
      "id": 733,
      "name": "Cargo Jacket",
      "price": 59.99,
      "description": "Versatile cargo jacket.",
      "color": "camouflage",
      "material": "cotton",
      "image": "https://i.ibb.co/SvMppGV/240-F-474792959-5-ZDq-KMQB55-Fvot7-WKlv-Nv-Xciv9v-TACXB.jpg",
      "brand": "Alpha Industries",
      "rating": 4.8,
      "subcategory": "jackets",
      "category": "man",
      "Quantity": 50
   },
   {
      "id": 734,
      "name": "Wrap Skirt",
      "price": 39.99,
      "description": "Stylish wrap skirt.",
      "color": "black",
      "material": "polyester",
      "image": "https://i.ibb.co/jGsdBzb/240-F-228558648-Ib-UYENc9h-Kf-OTlle-Fgrksp-Gs-Ed-HIC9-KK.jpg",
      "brand": "Forever 21",
      "rating": 4.7,
      "subcategory": "skirts",
      "category": "women",
      "Quantity": 50
   },
   {
      "id": 735,
      "name": "Hawaiian Shirt",
      "price": 34.99,
      "description": "Classic Hawaiian print shirt.",
      "color": "blue/pink",
      "material": "cotton",
      "image": "https://i.ibb.co/F6t74NQ/240-F-597476417-W8gr-HQL71c3we-Qsh-Nfyxhhpqx-FSUCo-H4.jpg",
      "brand": "Pacific Legend",
      "rating": 4.5,
      "subcategory": "shirts",
      "category": "man",
      "Quantity": 50
   },
   {
      "id": 736,
      "name": "Rash Guard",
      "price": 39.99,
      "description": "Protective rash guard.",
      "color": "black",
      "material": "nylon/spandex",
      "image": "https://i.ibb.co/0y1VGpb/240-F-430108600-RUp8-R44-Ry-Rj-Sfv0-XGe9-M75-Mo-Io2-REd-LW.jpg",
      "brand": "Quiksilver",
      "rating": 4.7,
      "subcategory": "swimwear",
      "category": "man",
      "Quantity": 50
   },
   {
      "id": 737,
      "name": "Floral Dress",
      "price": 49.99,
      "description": "Chic floral print dress.",
      "color": "floral",
      "material": "polyester",
      "image": "https://i.ibb.co/hLPB7HF/240-F-266043643-8-DINB2-Qqk1-QCElis-MIRncmfdt-VJJYPb-X.jpg",
      "brand": "Forever 21",
      "rating": 4.8,
      "subcategory": "dresses",
      "category": "women",
      "Quantity": 50
   },
   {
      "id": 804,
      "name": "Denim Overalls",
      "price": 39.99,
      "description": "Adorable denim overalls for kids.",
      "color": "blue",
      "material": "denim",
      "image": "https://i.ibb.co/DLdpCSK/240-F-614780746-OEjmcc-SGr-YWET88u-JHd-YBIl-Ew-SGvqug-L.jpg",
      "brand": "Carter's",
      "rating": 4.7,
      "subcategory": "clothes",
      "category": "kids",
      "Quantity": 50,
      "size": [
         "S",
         "M",
         "L"
      ]
   },
   {
      "id": 805,
      "name": "Colorful Graphic T-Shirt",
      "price": 19.99,
      "description": "Cool graphic t-shirt for kids.",
      "color": "blue",
      "material": "cotton",
      "image": "https://i.ibb.co/c1K7J81/images-3.jpg",
      "brand": "Nike",
      "rating": 4.6,
      "subcategory": "clothes",
      "category": "kids",
      "Quantity": 50,
      "size": [
         "S",
         "M"
      ]
   },
   {
      "id": 806,
      "name": "Kids' Backpack",
      "price": 29.99,
      "description": "Spacious and stylish backpack for kids.",
      "color": "purple",
      "material": "nylon",
      "image": "https://i.ibb.co/Gd9H73c/240-F-427954867-Zg-OGNSb-JMnj-E4by-Bc-VRp-Gu-Eu-RI694x-WU.jpg",
      "brand": "Jansport",
      "rating": 4.5,
      "subcategory": "bags",
      "category": "kids",
      "Quantity": 50,
      "size": [
         "One Size"
      ]
   },
   {
      "id": 807,
      "name": "Kids' Sweatshirt",
      "price": 34.99,
      "description": "Cozy sweatshirt for kids.",
      "color": "gray",
      "material": "fleece",
      "image": "https://i.ibb.co/ZN96c2L/240-F-294430586-JOdsc6zq-QC0ah-XMNMLNg-Et-Ra-PQUxi-SBr.jpg",
      "brand": "H&M Kids",
      "rating": 4.7,
      "subcategory": "clothes",
      "category": "kids",
      "Quantity": 50,
      "size": [
         "S",
         "M",
         "L"
      ]
   },
   {
      "id": 808,
      "name": "Kids' Party Dress",
      "price": 49.99,
      "description": "Elegant party dress for kids.",
      "color": "white",
      "material": "satin",
      "image": "https://i.ibb.co/8xhQQWw/240-F-318308547-FALKncf-Ws-Tmjzwd0y0mu-Ne-CFOULPLB7-Q.jpg",
      "brand": "Zara Kids",
      "rating": 4.9,
      "subcategory": "clothes",
      "category": "kids",
      "Quantity": 50,
      "size": [
         "M",
         "L"
      ]
   },
   {
      "id": 809,
      "name": "Stylish Hat",
      "price": 19.99,
      "description": "Stylish baseball cap for kids.",
      "color": "red",
      "material": "cotton",
      "image": "https://i.ibb.co/Gxy7FYs/240-F-613538790-ZQqmhgkjx2gb-Fx2-Pm-Lwh0-KJyg-If-OAZek.jpg",
      "brand": "Adidas",
      "rating": 4.6,
      "subcategory": "hats",
      "category": "kids",
      "Quantity": 50,
      "size": [
         "M",
         "L"
      ]
   },
   {
      "id": 810,
      "name": "Casual Shirt",
      "price": 24.99,
      "description": "Comfortable casual shorts for kids.",
      "color": "green",
      "material": "cotton",
      "image": "https://i.ibb.co/hXmmwCH/240-F-622120265-HY3bi4i0-DNk-Edw-Q4-Rd-ODi3p1-Ac0-A9-NAu.jpg",
      "brand": "Old Navy",
      "rating": 4.6,
      "subcategory": "clothes",
      "category": "kids",
      "Quantity": 50,
      "size": [
         "S",
         "M",
         "L"
      ]
   },
   {
      "id": 811,
      "name": "Floral Maxi",
      "price": 54.99,
      "description": "Chic floral maxi dress for women.",
      "color": "floral",
      "material": "polyester",
      "image": "https://i.ibb.co/2STr4zW/240-F-227596906-g-Z8a-RDhjf-Hkl-Srpz-Xdgp85-JJgtum4-J9a.jpg",
      "brand": "Forever 21",
      "rating": 4.7,
      "subcategory": "clothes",
      "category": "women",
      "Quantity": 50,
      "size": [
         "S",
         "M",
         "L"
      ]
   },
   {
      "id": 812,
      "name": " Ruffled Blouse",
      "price": 39.99,
      "description": "Feminine ruffled blouse for women.",
      "color": "pink",
      "material": "polyester",
      "image": "https://i.ibb.co/vQwtCJZ/240-F-183229345-Ff-G8-WLikhk-NQd-Aa6-ANC5-PBfr-ZK8tx8-W3.jpg",
      "brand": "Zara",
      "rating": 4.8,
      "subcategory": "clothes",
      "category": "women",
      "Quantity": 50,
      "size": [
         "S",
         "M",
         "L"
      ]
   }
]